persian_numbers/__init__.py
persian_numbers/templatetags/__init__.py
persian_numbers/templatetags/persian_filters.py
persian_numbers-1.1.dist-info/LICENSE
persian_numbers-1.1.dist-info/METADATA
persian_numbers-1.1.dist-info/WHEEL
persian_numbers-1.1.dist-info/top_level.txt
persian_numbers-1.1.dist-info/RECORD
